dlogs/__init__.py
dlogs/cli.py
dlogs/assets/docker-compose.yml
dlogs/assets/config/prometheus.yml
dlogs/assets/config/promtail-config.yml
dlogs/assets/config/promtail.yml
dlogs/assets/dashboards/docker_containers.json
dlogs/assets/dashboards/loki_logs.json
dlogs/assets/dashboards/nvidia_gpu.json
dlogs/assets/dashboards/windows_exporter.json
dlogs/assets/provisioning/dashboards/dlogs.yml
dlogs/assets/provisioning/datasources/dlogs.yml
motidivya_dlogs-0.1.6.dist-info/licenses/LICENSE
motidivya_dlogs-0.1.6.dist-info/METADATA
motidivya_dlogs-0.1.6.dist-info/WHEEL
motidivya_dlogs-0.1.6.dist-info/entry_points.txt
motidivya_dlogs-0.1.6.dist-info/top_level.txt
motidivya_dlogs-0.1.6.dist-info/RECORD
