Metadata-Version: 2.4
Name: motidivya-dlogs
Version: 0.1.6
Summary: dLogs - one command installer/bootstrapper for your logging & monitoring stack
Author: Divyesh Vishwakarma
License: MIT
Requires-Python: >=3.9
License-File: LICENSE
Requires-Dist: rich>=13.7.0
Dynamic: license-file
